[{
    "book1":{
        "title": "100 años de soledad",
        "author": "Gabriel García Marquez",
        "year": "1967",
        "chapters": {
            "chapter1": 58,
            "chapter2": 74,
            "chapter3": 87,
            "chapter4": 71,
            "chapter5": 67
        }
    },
    "book2":{
        "title": "Crimen y Castigo",
        "author": "Fiódor Dostoyevski",
        "year": "1866",
        "chapters": {
            "chapter1": 106,
            "chapter2": 201,
            "chapter3": 98,
            "chapter4": 150
        }
    },
    "book3":{
        "title": "La metamosfosis",
        "author": "Franz kafka",
        "year": "1915",
        "chapters": {
        }
    }
}]